pkg/__init__.py
pkg/bmi.py
pkg/bmi_intrin.c
pkg/bmi_intrin.so
pkg/makefile
x86bmi/__init__.py
x86bmi/bmi.py
x86bmi/bmi_intrin.c
x86bmi/bmi_intrin.so
x86bmi/makefile
x86bmi-0.0.3.dist-info/METADATA
x86bmi-0.0.3.dist-info/WHEEL
x86bmi-0.0.3.dist-info/top_level.txt
x86bmi-0.0.3.dist-info/RECORD
