Metadata-Version: 2.1
Name: x86bmi
Version: 0.0.3
Summary: x86 intrin for bmi instructions
Home-page: UNKNOWN
Author: noname00
Author-email: author@example.com
License: UNKNOWN
Platform: UNKNOWN
Classifier: Programming Language :: Python :: 3
Classifier: Operating System :: OS Independent
Requires-Python: >=3.6
Requires-Dist: numpy
